python_hue_v2/__about__.py
python_hue_v2/__init__.py
python_hue_v2/bridge.py
python_hue_v2/grouped_light.py
python_hue_v2/hue.py
python_hue_v2/light.py
python_hue_v2/mdns.py
python_hue_v2/room/__init__.py
python_hue_v2/room/resource_identifier_get.py
python_hue_v2/room/room.py
python_hue_v2/room/room_get.py
python_hue_v2/scene/__init__.py
python_hue_v2/scene/group.py
python_hue_v2/scene/meta_data.py
python_hue_v2/scene/scene.py
python_hue_v2/scene/target.py
python_hue_v2/scene/action/__init__.py
python_hue_v2/scene/action/action.py
python_hue_v2/scene/action/action_get.py
python_hue_v2/scene/action/action_post.py
python_hue_v2/scene/action/action_put.py
python_hue_v2/zone/__init__.py
python_hue_v2/zone/resource_identifier_get.py
python_hue_v2/zone/zone.py
python_hue_v2/zone/zone_get.py
python_hue_v2-2.2.1.dist-info/METADATA
python_hue_v2-2.2.1.dist-info/WHEEL
python_hue_v2-2.2.1.dist-info/licenses/LICENSE
python_hue_v2-2.2.1.dist-info/RECORD
