Metadata-Version: 2.4
Name: python-hue-v2
Version: 2.2.1
Summary: A python library to control the Philips Hue lighting system.
Project-URL: Documentation, https://github.com/FengChendian/python-hue-v2#readme
Project-URL: Issues, https://github.com/FengChendian/python-hue-v2/issues
Project-URL: Source, https://github.com/FengChendian/python-hue-v2
Author-email: Yichen Zhao <njuzhaoyichen@gmail.com>
License-Expression: MIT
License-File: LICENSE
Classifier: Development Status :: 4 - Beta
Classifier: Programming Language :: Python
Classifier: Programming Language :: Python :: 3.8
Classifier: Programming Language :: Python :: 3.9
Classifier: Programming Language :: Python :: 3.10
Classifier: Programming Language :: Python :: 3.11
Classifier: Programming Language :: Python :: Implementation :: CPython
Classifier: Programming Language :: Python :: Implementation :: PyPy
Requires-Python: >=3.8
Requires-Dist: requests>=2.30.0
Requires-Dist: zeroconf>=0.62.0
